{
    "data": [
        {
            "iteration": 1,
            "type": "frontend",
            "load": 8839.127872716559,
            "run": 6712.911165808906
        },
        {
            "iteration": 2,
            "type": "frontend",
            "load": 9894.459102902374,
            "run": 7471.9800747198005
        },
        {
            "iteration": 3,
            "type": "frontend",
            "load": 9404.388714733543,
            "run": 6979.990693345742
        },
        {
            "iteration": 4,
            "type": "frontend",
            "load": 9124.087591240876,
            "run": 7513.1480090157775
        },
        {
            "iteration": 5,
            "type": "frontend",
            "load": 7672.634271099744,
            "run": 5941.770647653
        },
        {
            "iteration": 6,
            "type": "frontend",
            "load": 8698.173383589447,
            "run": 7073.803348266918
        },
        {
            "iteration": 7,
            "type": "frontend",
            "load": 8549.444286121403,
            "run": 7367.387033398822
        },
        {
            "iteration": 8,
            "type": "frontend",
            "load": 8782.201405152226,
            "run": 7447.864945382324
        },
        {
            "iteration": 9,
            "type": "frontend",
            "load": 9222.256378727328,
            "run": 6890.2158934313275
        },
        {
            "iteration": 10,
            "type": "frontend",
            "load": 8957.897879964168,
            "run": 6560.24491581019
        },
        {
            "iteration": 11,
            "type": "frontend",
            "load": 8941.877794336811,
            "run": 7103.954534690978
        },
        {
            "iteration": 12,
            "type": "frontend",
            "load": 9174.311926605504,
            "run": 6949.270326615705
        },
        {
            "iteration": 13,
            "type": "frontend",
            "load": 9478.67298578199,
            "run": 6989.748369058714
        },
        {
            "iteration": 14,
            "type": "frontend",
            "load": 9469.69696969697,
            "run": 7159.904534606205
        },
        {
            "iteration": 15,
            "type": "frontend",
            "load": 8099.352051835853,
            "run": 6690.454950936663
        },
        {
            "iteration": 16,
            "type": "frontend",
            "load": 8726.003490401396,
            "run": 7735.946364105209
        },
        {
            "iteration": 17,
            "type": "frontend",
            "load": 9003.60144057623,
            "run": 6568.863586599518
        },
        {
            "iteration": 18,
            "type": "frontend",
            "load": 8223.684210526315,
            "run": 6317.119393556538
        },
        {
            "iteration": 19,
            "type": "frontend",
            "load": 9826.40026203734,
            "run": 7371.007371007371
        },
        {
            "iteration": 20,
            "type": "frontend",
            "load": 9765.625,
            "run": 7608.41998478316
        },
        {
            "iteration": 10,
            "type": "raw",
            "load": 8472.182999152781,
            "run": 7676.560900716479
        },
        {
            "iteration": 11,
            "type": "raw",
            "load": 8764.241893076249,
            "run": 7874.0157480314965
        },
        {
            "iteration": 11,
            "type": "raw",
            "load": 7824.726134585289,
            "run": 7522.567703109328
        },
        {
            "iteration": 12,
            "type": "raw",
            "load": 8782.201405152226,
            "run": 7824.726134585289
        },
        {
            "iteration": 12,
            "type": "raw",
            "load": 8878.366380585972,
            "run": 6153.846153846154
        },
        {
            "iteration": 13,
            "type": "raw",
            "load": 8244.023083264634,
            "run": 7882.291119285339
        },
        {
            "iteration": 13,
            "type": "raw",
            "load": 8198.961464881115,
            "run": 7620.01524003048
        },
        {
            "iteration": 14,
            "type": "raw",
            "load": 7530.120481927711,
            "run": 7274.4907856450045
        },
        {
            "iteration": 14,
            "type": "raw",
            "load": 8573.878250928838,
            "run": 7052.186177715092
        },
        {
            "iteration": 15,
            "type": "raw",
            "load": 9428.032683846637,
            "run": 6914.035492048859
        },
        {
            "iteration": 15,
            "type": "raw",
            "load": 8764.241893076249,
            "run": 7723.99588053553
        },
        {
            "iteration": 16,
            "type": "raw",
            "load": 9302.32558139535,
            "run": 7737.941707505804
        },
        {
            "iteration": 16,
            "type": "raw",
            "load": 8665.511265164645,
            "run": 5652.911249293386
        },
        {
            "iteration": 17,
            "type": "raw",
            "load": 9762.447120078099,
            "run": 7457.121551081283
        },
        {
            "iteration": 17,
            "type": "raw",
            "load": 8441.193021947101,
            "run": 7006.0719290051375
        },
        {
            "iteration": 18,
            "type": "raw",
            "load": 8434.07365757661,
            "run": 7208.073041806823
        },
        {
            "iteration": 18,
            "type": "raw",
            "load": 9526.83391552874,
            "run": 7511.266900350526
        },
        {
            "iteration": 19,
            "type": "raw",
            "load": 9250.693802035152,
            "run": 7498.125468632842
        },
        {
            "iteration": 19,
            "type": "raw",
            "load": 8928.57142857143,
            "run": 7444.168734491315
        },
        {
            "iteration": 20,
            "type": "raw",
            "load": 9775.171065493647,
            "run": 7604.5627376425855
        }
    ],
    "results": {
        "averages_load": {
            "raw": 8777,
            "frontend": 8992
        },
        "averages_run": {
            "raw": 7331,
            "frontend": 7022
        },
        "execution_time": {
            "raw": 8.088906563,
            "frontend": 10.607523404
        },
        "percents": {
            "average_load": 102,
            "average_run": 95,
            "execution_time": 131
        }
    }
}
