{
    "data": [
        {
            "iteration": 1,
            "type": "frontend",
            "load": 12234.910277324632,
            "run": 10714.285714285714
        },
        {
            "iteration": 2,
            "type": "frontend",
            "load": 12733.446519524618,
            "run": 9202.453987730061
        },
        {
            "iteration": 3,
            "type": "frontend",
            "load": 10431.15438108484,
            "run": 9541.984732824427
        },
        {
            "iteration": 4,
            "type": "frontend",
            "load": 12295.081967213115,
            "run": 10869.565217391304
        },
        {
            "iteration": 5,
            "type": "frontend",
            "load": 12274.959083469721,
            "run": 9715.025906735751
        },
        {
            "iteration": 6,
            "type": "frontend",
            "load": 11061.946902654867,
            "run": 11261.261261261261
        },
        {
            "iteration": 7,
            "type": "frontend",
            "load": 13416.815742397137,
            "run": 10744.985673352436
        },
        {
            "iteration": 8,
            "type": "frontend",
            "load": 12820.51282051282,
            "run": 9778.357235984355
        },
        {
            "iteration": 9,
            "type": "frontend",
            "load": 8532.423208191127,
            "run": 9036.144578313253
        },
        {
            "iteration": 10,
            "type": "frontend",
            "load": 12626.262626262625,
            "run": 9842.51968503937
        },
        {
            "iteration": 11,
            "type": "frontend",
            "load": 12175.324675324675,
            "run": 9179.926560587515
        },
        {
            "iteration": 12,
            "type": "frontend",
            "load": 12135.922330097088,
            "run": 9894.459102902374
        },
        {
            "iteration": 13,
            "type": "frontend",
            "load": 12647.554806070826,
            "run": 9433.962264150943
        },
        {
            "iteration": 14,
            "type": "frontend",
            "load": 12315.27093596059,
            "run": 9933.774834437087
        },
        {
            "iteration": 15,
            "type": "frontend",
            "load": 12647.554806070826,
            "run": 9640.102827763496
        },
        {
            "iteration": 16,
            "type": "frontend",
            "load": 10548.523206751055,
            "run": 9677.41935483871
        },
        {
            "iteration": 17,
            "type": "frontend",
            "load": 12776.831345826235,
            "run": 10445.682451253482
        },
        {
            "iteration": 18,
            "type": "frontend",
            "load": 12931.034482758621,
            "run": 10608.203677510608
        },
        {
            "iteration": 19,
            "type": "frontend",
            "load": 13297.872340425532,
            "run": 11045.655375552284
        },
        {
            "iteration": 20,
            "type": "frontend",
            "load": 12155.591572123176,
            "run": 11177.347242921014
        },
        {
            "iteration": 10,
            "type": "raw",
            "load": 11904.761904761905,
            "run": 8886.255924170617
        },
        {
            "iteration": 11,
            "type": "raw",
            "load": 12019.23076923077,
            "run": 10460.251046025105
        },
        {
            "iteration": 11,
            "type": "raw",
            "load": 12038.52327447833,
            "run": 10822.510822510823
        },
        {
            "iteration": 12,
            "type": "raw",
            "load": 10533.707865168539,
            "run": 10259.917920656635
        },
        {
            "iteration": 12,
            "type": "raw",
            "load": 11591.962905718701,
            "run": 10760.401721664275
        },
        {
            "iteration": 13,
            "type": "raw",
            "load": 11682.242990654206,
            "run": 10638.297872340425
        },
        {
            "iteration": 13,
            "type": "raw",
            "load": 12335.526315789473,
            "run": 10273.972602739726
        },
        {
            "iteration": 14,
            "type": "raw",
            "load": 11094.674556213018,
            "run": 9640.102827763496
        },
        {
            "iteration": 14,
            "type": "raw",
            "load": 12057.877813504823,
            "run": 10431.15438108484
        },
        {
            "iteration": 15,
            "type": "raw",
            "load": 11737.089201877934,
            "run": 10683.760683760684
        },
        {
            "iteration": 15,
            "type": "raw",
            "load": 9590.79283887468,
            "run": 10948.905109489051
        },
        {
            "iteration": 16,
            "type": "raw",
            "load": 11380.880121396054,
            "run": 10373.443983402489
        },
        {
            "iteration": 16,
            "type": "raw",
            "load": 12479.20133111481,
            "run": 9293.68029739777
        },
        {
            "iteration": 17,
            "type": "raw",
            "load": 12437.810945273632,
            "run": 10176.3907734057
        },
        {
            "iteration": 17,
            "type": "raw",
            "load": 11885.895404120443,
            "run": 10623.229461756375
        },
        {
            "iteration": 18,
            "type": "raw",
            "load": 11398.176291793314,
            "run": 10699.001426533523
        },
        {
            "iteration": 18,
            "type": "raw",
            "load": 12234.910277324632,
            "run": 10822.510822510823
        },
        {
            "iteration": 19,
            "type": "raw",
            "load": 9881.422924901186,
            "run": 11363.636363636364
        },
        {
            "iteration": 19,
            "type": "raw",
            "load": 11942.675159235669,
            "run": 10683.760683760684
        },
        {
            "iteration": 20,
            "type": "raw",
            "load": 11980.830670926518,
            "run": 9236.453201970444
        }
    ],
    "results": {
        "averages_load": {
            "raw": 11610,
            "frontend": 12102
        },
        "averages_run": {
            "raw": 10353,
            "frontend": 10087
        },
        "execution_time": {
            "raw": 2.156263067,
            "frontend": 10.647684261
        },
        "percents": {
            "average_load": 104,
            "average_run": 97,
            "execution_time": 493
        }
    }
}
